LICENSE
MANIFEST.in
README.md
requirements.txt
setup.py
django_mailcenter/__init__.py
django_mailcenter/admin.py
django_mailcenter/apps.py
django_mailcenter/client.py
django_mailcenter/models.py
django_mailcenter/services.py
django_mailcenter/settings.py
django_mailcenter/tests.py
django_mailcenter/urls.py
django_mailcenter/views.py
django_mailcenter.egg-info/PKG-INFO
django_mailcenter.egg-info/SOURCES.txt
django_mailcenter.egg-info/dependency_links.txt
django_mailcenter.egg-info/not-zip-safe
django_mailcenter.egg-info/requires.txt
django_mailcenter.egg-info/top_level.txt
django_mailcenter/locale/zh_Hans/LC_MESSAGES/django.mo
django_mailcenter/locale/zh_Hans/LC_MESSAGES/django.po
django_mailcenter/management/__init__.py
django_mailcenter/management/commands/__init__.py
django_mailcenter/management/commands/django_mailcenter_sendmails.py
django_mailcenter/migrations/0001_initial.py
django_mailcenter/migrations/0002_auto_20200901_2146.py
django_mailcenter/migrations/0003_auto_20201123_1719.py
django_mailcenter/migrations/__init__.py